blog_travis_docker/__init__.py
blog_travis_docker/__main__.py
blog_travis_docker/hello.py
blog_travis_docker/tests/__init__.py
blog_travis_docker/tests/test_hello.py
blog_travis_docker/tests/test_main.py
blog_travis_docker-0.1.3.dist-info/top_level.txt
blog_travis_docker-0.1.3.dist-info/entry_points.txt
blog_travis_docker-0.1.3.dist-info/METADATA
blog_travis_docker-0.1.3.dist-info/DESCRIPTION.rst
blog_travis_docker-0.1.3.dist-info/LICENSE.txt
blog_travis_docker-0.1.3.dist-info/metadata.json
blog_travis_docker-0.1.3.dist-info/WHEEL
blog_travis_docker-0.1.3.dist-info/RECORD
