Metadata-Version: 2.0
Name: blog-travis-docker
Version: 0.1.3
Summary: Code for a blog post on using Docker with Travis CI
Home-page: https://github.com/JayH5/blog-travis-docker-part2
Author: Jamie Hewland
Author-email: jamie@praekelt.org
License: BSD-3-Clause
Platform: UNKNOWN
Classifier: Development Status :: 3 - Alpha
Classifier: License :: OSI Approved :: BSD License
Classifier: Programming Language :: Python :: 2
Classifier: Programming Language :: Python :: 2.7
Classifier: Programming Language :: Python :: 3
Classifier: Programming Language :: Python :: 3.5
Classifier: Programming Language :: Python :: 3.6
